LICENSE.txt
MANIFEST.in
README.md
hplusminus_tests.py
requirements.txt
setup.cfg
setup.py
examples/alternative_model.txt
examples/alternative_model_normalized_residuals.txt
examples/true_model_normalized_residuals.txt
hplusminus/__init__.py
hplusminus/evaluate.py
hplusminus/io.py
hplusminus/rld.py
hplusminus/sid.py
hplusminus.egg-info/PKG-INFO
hplusminus.egg-info/SOURCES.txt
hplusminus.egg-info/dependency_links.txt
hplusminus.egg-info/requires.txt
hplusminus.egg-info/top_level.txt
hplusminus/gsp/README.txt
hplusminus/gsp/coeffs_both_I0.npy
hplusminus/gsp/coeffs_both_alpha.npy
hplusminus/gsp/coeffs_both_beta.npy
hplusminus/gsp/coeffs_both_simple_I0.npy
hplusminus/gsp/coeffs_both_simple_alpha.npy
hplusminus/gsp/coeffs_both_simple_beta.npy
hplusminus/gsp/coeffs_h_I0.npy
hplusminus/gsp/coeffs_h_alpha.npy
hplusminus/gsp/coeffs_h_beta.npy
hplusminus/gsp/coeffs_h_simple_I0.npy
hplusminus/gsp/coeffs_h_simple_alpha.npy
hplusminus/gsp/coeffs_h_simple_beta.npy
hplusminus/gsp/knots_both_I0.npy
hplusminus/gsp/knots_both_alpha.npy
hplusminus/gsp/knots_both_beta.npy
hplusminus/gsp/knots_both_simple_I0.npy
hplusminus/gsp/knots_both_simple_alpha.npy
hplusminus/gsp/knots_both_simple_beta.npy
hplusminus/gsp/knots_h_I0.npy
hplusminus/gsp/knots_h_alpha.npy
hplusminus/gsp/knots_h_beta.npy
hplusminus/gsp/knots_h_simple_I0.npy
hplusminus/gsp/knots_h_simple_alpha.npy
hplusminus/gsp/knots_h_simple_beta.npy
hplusminus/test/__init__.py
hplusminus/test/test_hpm.py
img/overview.png
ipynb/generate_models_for_residuals.ipynb
ipynb/hplusminus_statistical_power.ipynb
ipynb/hplusminus_tests.ipynb
ipynb/test_ipynb_offline.sh