Metadata-Version: 2.1
Name: hplusminus
Version: 1.0.1
Summary: evaluate test statistics for normalized residuals
Home-page: https://github.com/bio-phys/hplusminus
Author: Juergen Koefinger (MPI for Biophysics), Klaus Reuter (Max Planck Computing and Data Facility)
Author-email: juergen.koefinger@biophys.mpg.de
License: UNKNOWN
Platform: UNKNOWN
Classifier: Programming Language :: Python :: 3
Classifier: License :: OSI Approved :: MIT License
Classifier: Operating System :: OS Independent
Requires: numpy
Requires: scipy
Requires: mpmath
Requires-Python: >=3.6
Provides-Extra: jupyter
Provides-Extra: pytest
